quickscrape/__init__.py
quickscrape/core.py
quickscrape/extractors/__init__.py
quickscrape/extractors/common.py
quickscrape/extractors/email.py
quickscrape/extractors/links.py
quickscrape/extractors/table.py
quickscrape/utils/__init__.py
quickscrape/utils/parser.py
quickscrape/utils/request.py
quickscrape-0.1.1.dist-info/LICENSE
quickscrape-0.1.1.dist-info/METADATA
quickscrape-0.1.1.dist-info/WHEEL
quickscrape-0.1.1.dist-info/top_level.txt
quickscrape-0.1.1.dist-info/RECORD
