Metadata-Version: 2.2
Name: quickscrape
Version: 0.1.1
Summary: A simple library for extracting common data types from web pages
Author-email: Utku Ayaz Akkas <akkas@ieee.org>
Project-URL: Homepage, https://github.com/akkasayaz/quickscrape
Project-URL: Bug Tracker, https://github.com/akkasayaz/quickscrape/issues
Classifier: Programming Language :: Python :: 3
Classifier: License :: OSI Approved :: MIT License
Classifier: Operating System :: OS Independent
Requires-Python: >=3.7
License-File: LICENSE
Requires-Dist: beautifulsoup4>=4.9.0
Requires-Dist: requests>=2.25.0
Requires-Dist: pandas>=1.2.0
